<?xml version="1.0" encoding="UTF-8"?>
<!--oriflamms data file-->
<OriData>
    <validation>
        <v id="w_mss-dates_12107" ok="2" left="0" right="0" imgsig=""/>
        <v id="w_mss-dates_12114" ok="2" left="0" right="0" imgsig=""/>
        <v id="w_mss-dates_12108" ok="2" left="0" right="0" imgsig=""/>
        <v id="w_mss-dates_12113" ok="2" left="0" right="0" imgsig=""/>
        <v id="w_mss-dates_12109" ok="2" left="0" right="0" imgsig=""/>
        <v id="w_mss-dates_12112" ok="2" left="0" right="0" imgsig=""/>
        <v id="w_mss-dates_12110" ok="2" left="0" right="0" imgsig=""/>
        <v id="w_mss-dates_12111" ok="2" left="0" right="0" imgsig=""/>
        <v id="w_mss-dates_12115" ok="2" left="0" right="0" imgsig=""/>
        <v id="w_mss-dates_12116" ok="2" left="0" right="0" imgsig=""/>
        <v id="w_mss-dates_12149" ok="2" left="0" right="0" imgsig=""/>
        <v id="w_mss-dates_12117" ok="2" left="0" right="0" imgsig=""/>
        <v id="w_mss-dates_12148" ok="2" left="0" right="0" imgsig=""/>
        <v id="w_mss-dates_12118" ok="2" left="0" right="0" imgsig=""/>
        <v id="w_mss-dates_12147" ok="2" left="0" right="0" imgsig=""/>
        <v id="w_mss-dates_12119" ok="2" left="0" right="0" imgsig=""/>
        <v id="w_mss-dates_12146" ok="2" left="0" right="0" imgsig=""/>
        <v id="w_mss-dates_12120" ok="2" left="0" right="0" imgsig=""/>
        <v id="w_mss-dates_12121" ok="2" left="0" right="0" imgsig=""/>
        <v id="w_mss-dates_12122" ok="2" left="0" right="0" imgsig=""/>
        <v id="w_mss-dates_12123" ok="2" left="0" right="0" imgsig=""/>
        <v id="w_mss-dates_12124" ok="2" left="0" right="0" imgsig=""/>
        <v id="w_mss-dates_12168" ok="2" left="0" right="0" imgsig=""/>
        <v id="w_mss-dates_12125" ok="2" left="0" right="0" imgsig=""/>
        <v id="w_mss-dates_12169" ok="2" left="0" right="0" imgsig=""/>
        <v id="w_mss-dates_12126" ok="2" left="0" right="0" imgsig=""/>
        <v id="w_mss-dates_12139" ok="2" left="0" right="0" imgsig=""/>
        <v id="w_mss-dates_12127" ok="2" left="0" right="0" imgsig=""/>
        <v id="w_mss-dates_12138" ok="2" left="0" right="0" imgsig=""/>
        <v id="w_mss-dates_12128" ok="2" left="0" right="0" imgsig=""/>
        <v id="w_mss-dates_12137" ok="2" left="0" right="0" imgsig=""/>
        <v id="w_mss-dates_12164" ok="2" left="0" right="0" imgsig=""/>
        <v id="w_mss-dates_12129" ok="2" left="0" right="0" imgsig=""/>
        <v id="w_mss-dates_12136" ok="2" left="0" right="0" imgsig=""/>
        <v id="w_mss-dates_12165" ok="2" left="0" right="0" imgsig=""/>
        <v id="w_mss-dates_12130" ok="2" left="0" right="0" imgsig=""/>
        <v id="w_mss-dates_12163" ok="2" left="0" right="0" imgsig=""/>
        <v id="w_mss-dates_12131" ok="2" left="0" right="0" imgsig=""/>
        <v id="w_mss-dates_12162" ok="2" left="0" right="0" imgsig=""/>
        <v id="w_mss-dates_12132" ok="2" left="0" right="0" imgsig=""/>
        <v id="w_mss-dates_12161" ok="2" left="0" right="0" imgsig=""/>
        <v id="w_mss-dates_12133" ok="2" left="0" right="0" imgsig=""/>
        <v id="w_mss-dates_12160" ok="2" left="0" right="0" imgsig=""/>
        <v id="w_mss-dates_12134" ok="2" left="0" right="0" imgsig=""/>
        <v id="w_mss-dates_12167" ok="2" left="0" right="0" imgsig=""/>
        <v id="w_mss-dates_12135" ok="2" left="0" right="0" imgsig=""/>
        <v id="w_mss-dates_12166" ok="2" left="0" right="0" imgsig=""/>
        <v id="w_mss-dates_12140" ok="2" left="0" right="0" imgsig=""/>
        <v id="w_mss-dates_12141" ok="2" left="0" right="0" imgsig=""/>
        <v id="w_mss-dates_12142" ok="2" left="0" right="0" imgsig=""/>
        <v id="w_mss-dates_12143" ok="2" left="0" right="0" imgsig=""/>
        <v id="w_mss-dates_12144" ok="2" left="0" right="0" imgsig=""/>
        <v id="w_mss-dates_12145" ok="2" left="0" right="0" imgsig=""/>
        <v id="w_mss-dates_12150" ok="2" left="0" right="0" imgsig=""/>
        <v id="w_mss-dates_12151" ok="2" left="0" right="0" imgsig=""/>
        <v id="w_mss-dates_12152" ok="2" left="0" right="0" imgsig=""/>
        <v id="w_mss-dates_12153" ok="2" left="0" right="0" imgsig=""/>
        <v id="w_mss-dates_12154" ok="2" left="0" right="0" imgsig=""/>
        <v id="w_mss-dates_12155" ok="2" left="0" right="0" imgsig=""/>
        <v id="w_mss-dates_12156" ok="2" left="0" right="0" imgsig=""/>
        <v id="w_mss-dates_12157" ok="2" left="0" right="0" imgsig=""/>
        <v id="w_mss-dates_12158" ok="2" left="0" right="0" imgsig=""/>
        <v id="w_mss-dates_12159" ok="2" left="0" right="0" imgsig=""/>
        <v id="w_mss-dates_12170" ok="2" left="0" right="0" imgsig=""/>
        <v id="w_mss-dates_12171" ok="2" left="0" right="0" imgsig=""/>
        <v id="w_mss-dates_12172" ok="2" left="0" right="0" imgsig=""/>
        <v id="w_mss-dates_12173" ok="2" left="0" right="0" imgsig=""/>
        <v id="w_mss-dates_12174" ok="2" left="0" right="0" imgsig=""/>
        <v id="w_mss-dates_12175" ok="2" left="0" right="0" imgsig=""/>
        <v id="w_mss-dates_12176" ok="2" left="0" right="0" imgsig=""/>
        <v id="w_mss-dates_12177" ok="2" left="0" right="0" imgsig=""/>
        <v id="w_mss-dates_12178" ok="2" left="0" right="0" imgsig=""/>
        <v id="w_mss-dates_12179" ok="2" left="0" right="0" imgsig=""/>
        <v id="w_mss-dates_12180" ok="2" left="0" right="0" imgsig=""/>
        <v id="w_mss-dates_12181" ok="2" left="0" right="0" imgsig=""/>
        <v id="w_mss-dates_12182" ok="2" left="0" right="0" imgsig=""/>
        <v id="w_mss-dates_12183" ok="2" left="0" right="0" imgsig=""/>
        <v id="w_mss-dates_12184" ok="2" left="0" right="0" imgsig=""/>
        <v id="w_mss-dates_12185" ok="2" left="0" right="0" imgsig=""/>
        <v id="w_mss-dates_12186" ok="2" left="0" right="0" imgsig=""/>
        <v id="w_mss-dates_12187" ok="2" left="0" right="0" imgsig=""/>
        <v id="w_mss-dates_12188" ok="2" left="0" right="0" imgsig=""/>
        <v id="w_mss-dates_12189" ok="2" left="0" right="0" imgsig=""/>
        <v id="w_mss-dates_12190" ok="2" left="0" right="0" imgsig=""/>
        <v id="w_mss-dates_12191" ok="2" left="0" right="0" imgsig=""/>
        <v id="w_mss-dates_12192" ok="2" left="0" right="0" imgsig=""/>
        <v id="w_mss-dates_12193" ok="2" left="0" right="0" imgsig=""/>
        <v id="w_mss-dates_12194" ok="2" left="0" right="0" imgsig=""/>
        <v id="w_mss-dates_12195" ok="2" left="0" right="0" imgsig=""/>
        <v id="w_mss-dates_12196" ok="2" left="0" right="0" imgsig=""/>
        <v id="w_mss-dates_12197" ok="2" left="0" right="0" imgsig=""/>
        <v id="w_mss-dates_12198" ok="2" left="0" right="0" imgsig=""/>
        <v id="w_mss-dates_12199" ok="2" left="0" right="0" imgsig=""/>
        <v id="w_mss-dates_12200" ok="2" left="0" right="0" imgsig=""/>
        <v id="w_mss-dates_12201" ok="2" left="0" right="0" imgsig=""/>
        <v id="w_mss-dates_12202" ok="2" left="0" right="0" imgsig=""/>
        <v id="w_mss-dates_12203" ok="2" left="0" right="0" imgsig=""/>
        <v id="w_mss-dates_12204" ok="2" left="0" right="0" imgsig=""/>
        <v id="w_mss-dates_12205" ok="2" left="0" right="0" imgsig=""/>
        <v id="w_mss-dates_12206" ok="2" left="0" right="0" imgsig=""/>
        <v id="w_mss-dates_12207" ok="2" left="0" right="0" imgsig=""/>
        <v id="w_mss-dates_12208" ok="2" left="0" right="0" imgsig=""/>
        <v id="w_mss-dates_12209" ok="2" left="0" right="0" imgsig=""/>
        <v id="w_mss-dates_12210" ok="2" left="0" right="0" imgsig=""/>
        <v id="w_mss-dates_12211" ok="2" left="0" right="0" imgsig=""/>
        <v id="w_mss-dates_12212" ok="2" left="0" right="0" imgsig=""/>
        <v id="w_mss-dates_12213" ok="2" left="0" right="0" imgsig=""/>
    </validation>
    <medlines>
        <column id="col_IRHT_P_004956_1">
            <GraphicalLine lh="135">
                <LinearInterpolation>
                    <Point2DDouble x="324" y="271"/>
                    <Point2DDouble x="467" y="271"/>
                    <Point2DDouble x="675" y="271"/>
                    <Point2DDouble x="871" y="271"/>
                    <Point2DDouble x="1052" y="271"/>
                    <Point2DDouble x="1309" y="271"/>
                    <Point2DDouble x="1567" y="271"/>
                    <Point2DDouble x="1734" y="271"/>
                </LinearInterpolation>
            </GraphicalLine>
            <GraphicalLine lh="98">
                <LinearInterpolation>
                    <Point2DDouble x="323" y="370"/>
                    <Point2DDouble x="664" y="370"/>
                    <Point2DDouble x="913" y="370"/>
                    <Point2DDouble x="1235" y="370"/>
                    <Point2DDouble x="1321" y="370"/>
                    <Point2DDouble x="1467" y="370"/>
                    <Point2DDouble x="1570" y="370"/>
                    <Point2DDouble x="1726" y="370"/>
                </LinearInterpolation>
            </GraphicalLine>
            <GraphicalLine lh="102">
                <LinearInterpolation>
                    <Point2DDouble x="329" y="453"/>
                    <Point2DDouble x="461" y="453"/>
                    <Point2DDouble x="792" y="453"/>
                    <Point2DDouble x="982" y="453"/>
                    <Point2DDouble x="1194" y="453"/>
                    <Point2DDouble x="1290" y="453"/>
                    <Point2DDouble x="1540" y="453"/>
                    <Point2DDouble x="1700" y="453"/>
                </LinearInterpolation>
            </GraphicalLine>
            <GraphicalLine lh="103">
                <LinearInterpolation>
                    <Point2DDouble x="274" y="532"/>
                    <Point2DDouble x="472" y="532"/>
                    <Point2DDouble x="613" y="532"/>
                    <Point2DDouble x="851" y="532"/>
                    <Point2DDouble x="1067" y="532"/>
                    <Point2DDouble x="1378" y="532"/>
                    <Point2DDouble x="1662" y="532"/>
                    <Point2DDouble x="1729" y="532"/>
                </LinearInterpolation>
            </GraphicalLine>
            <GraphicalLine lh="98">
                <LinearInterpolation>
                    <Point2DDouble x="285" y="613"/>
                    <Point2DDouble x="388" y="613"/>
                    <Point2DDouble x="522" y="613"/>
                    <Point2DDouble x="599" y="613"/>
                    <Point2DDouble x="704" y="613"/>
                    <Point2DDouble x="804" y="613"/>
                    <Point2DDouble x="917" y="613"/>
                    <Point2DDouble x="1112" y="613"/>
                    <Point2DDouble x="1366" y="613"/>
                    <Point2DDouble x="1599" y="613"/>
                    <Point2DDouble x="1679" y="613"/>
                    <Point2DDouble x="1777" y="613"/>
                </LinearInterpolation>
            </GraphicalLine>
            <GraphicalLine lh="95">
                <LinearInterpolation>
                    <Point2DDouble x="285" y="696"/>
                    <Point2DDouble x="517" y="696"/>
                    <Point2DDouble x="628" y="696"/>
                    <Point2DDouble x="770" y="696"/>
                    <Point2DDouble x="1032" y="696"/>
                    <Point2DDouble x="1132" y="696"/>
                    <Point2DDouble x="1288" y="696"/>
                    <Point2DDouble x="1394" y="696"/>
                    <Point2DDouble x="1513" y="696"/>
                    <Point2DDouble x="1747" y="696"/>
                </LinearInterpolation>
            </GraphicalLine>
            <GraphicalLine lh="91">
                <LinearInterpolation>
                    <Point2DDouble x="284" y="778"/>
                    <Point2DDouble x="434" y="778"/>
                    <Point2DDouble x="597" y="778"/>
                    <Point2DDouble x="699" y="778"/>
                    <Point2DDouble x="767" y="778"/>
                    <Point2DDouble x="907" y="778"/>
                    <Point2DDouble x="1117" y="778"/>
                    <Point2DDouble x="1334" y="778"/>
                    <Point2DDouble x="1499" y="778"/>
                    <Point2DDouble x="1723" y="778"/>
                </LinearInterpolation>
            </GraphicalLine>
            <GraphicalLine lh="100">
                <LinearInterpolation>
                    <Point2DDouble x="282" y="857"/>
                    <Point2DDouble x="499" y="857"/>
                    <Point2DDouble x="756" y="857"/>
                    <Point2DDouble x="1002" y="857"/>
                    <Point2DDouble x="1304" y="857"/>
                    <Point2DDouble x="1605" y="857"/>
                    <Point2DDouble x="1797" y="857"/>
                </LinearInterpolation>
            </GraphicalLine>
            <GraphicalLine lh="100">
                <LinearInterpolation>
                    <Point2DDouble x="255" y="940"/>
                    <Point2DDouble x="487" y="940"/>
                    <Point2DDouble x="836" y="940"/>
                    <Point2DDouble x="906" y="940"/>
                    <Point2DDouble x="1134" y="940"/>
                    <Point2DDouble x="1296" y="940"/>
                    <Point2DDouble x="1459" y="940"/>
                    <Point2DDouble x="1768" y="940"/>
                </LinearInterpolation>
            </GraphicalLine>
            <GraphicalLine lh="97">
                <LinearInterpolation>
                    <Point2DDouble x="281" y="1023"/>
                    <Point2DDouble x="401" y="1023"/>
                    <Point2DDouble x="464" y="1023"/>
                    <Point2DDouble x="581" y="1023"/>
                    <Point2DDouble x="869" y="1023"/>
                    <Point2DDouble x="1054" y="1023"/>
                    <Point2DDouble x="1257" y="1023"/>
                    <Point2DDouble x="1336" y="1023"/>
                    <Point2DDouble x="1548" y="1023"/>
                    <Point2DDouble x="1732" y="1023"/>
                </LinearInterpolation>
            </GraphicalLine>
            <GraphicalLine lh="101">
                <LinearInterpolation>
                    <Point2DDouble x="276" y="1103"/>
                    <Point2DDouble x="439" y="1103"/>
                    <Point2DDouble x="644" y="1103"/>
                    <Point2DDouble x="725" y="1103"/>
                    <Point2DDouble x="826" y="1103"/>
                    <Point2DDouble x="1140" y="1103"/>
                    <Point2DDouble x="1371" y="1103"/>
                    <Point2DDouble x="1535" y="1103"/>
                    <Point2DDouble x="1612" y="1103"/>
                    <Point2DDouble x="1724" y="1103"/>
                </LinearInterpolation>
            </GraphicalLine>
            <GraphicalLine lh="95">
                <LinearInterpolation>
                    <Point2DDouble x="280" y="1185"/>
                    <Point2DDouble x="506" y="1185"/>
                    <Point2DDouble x="682" y="1185"/>
                    <Point2DDouble x="845" y="1185"/>
                    <Point2DDouble x="918" y="1185"/>
                    <Point2DDouble x="1091" y="1185"/>
                    <Point2DDouble x="1317" y="1185"/>
                    <Point2DDouble x="1386" y="1185"/>
                    <Point2DDouble x="1612" y="1185"/>
                    <Point2DDouble x="1744" y="1185"/>
                </LinearInterpolation>
            </GraphicalLine>
            <GraphicalLine lh="100">
                <LinearInterpolation>
                    <Point2DDouble x="277" y="1267"/>
                    <Point2DDouble x="472" y="1267"/>
                    <Point2DDouble x="609" y="1267"/>
                    <Point2DDouble x="681" y="1267"/>
                    <Point2DDouble x="743" y="1267"/>
                    <Point2DDouble x="795" y="1267"/>
                    <Point2DDouble x="951" y="1267"/>
                    <Point2DDouble x="1179" y="1267"/>
                    <Point2DDouble x="1393" y="1267"/>
                    <Point2DDouble x="1674" y="1267"/>
                    <Point2DDouble x="1749" y="1267"/>
                </LinearInterpolation>
            </GraphicalLine>
        </column>
    </medlines>
    <lineLinks>
        <ll id="line_IRHT_P_004956_1-9" col="col_IRHT_P_004956_1" n="8"/>
        <ll id="line_IRHT_P_004956_1-12" col="col_IRHT_P_004956_1" n="11"/>
        <ll id="line_IRHT_P_004956_1-1" col="col_IRHT_P_004956_1" n="0"/>
        <ll id="line_IRHT_P_004956_1-11" col="col_IRHT_P_004956_1" n="10"/>
        <ll id="line_IRHT_P_004956_1-2" col="col_IRHT_P_004956_1" n="1"/>
        <ll id="line_IRHT_P_004956_1-10" col="col_IRHT_P_004956_1" n="9"/>
        <ll id="line_IRHT_P_004956_1-3" col="col_IRHT_P_004956_1" n="2"/>
        <ll id="line_IRHT_P_004956_1-4" col="col_IRHT_P_004956_1" n="3"/>
        <ll id="line_IRHT_P_004956_1-5" col="col_IRHT_P_004956_1" n="4"/>
        <ll id="line_IRHT_P_004956_1-6" col="col_IRHT_P_004956_1" n="5"/>
        <ll id="line_IRHT_P_004956_1-7" col="col_IRHT_P_004956_1" n="6"/>
        <ll id="line_IRHT_P_004956_1-8" col="col_IRHT_P_004956_1" n="7"/>
        <ll id="line_IRHT_P_004956_1-13" col="col_IRHT_P_004956_1" n="12"/>
    </lineLinks>
</OriData>
